[
  {
    "label": "",
    "rows": [
      [
        {
          "name": "name",
          "fullWidth": true
        }
      ],
      [
        {
          "name": "website",
          "fullWidth": true
        }
      ],
      [
        {
          "name": "emailAddress",
          "fullWidth": true
        }
      ],
      [
        {
          "name": "phoneNumber",
          "fullWidth": true
        }
      ],
      [
        {
          "name": "type"
        },
        {
          "name": "industry"
        }
      ],
      [
        {
          "name": "description",
          "fullWidth": true
        }
      ]
    ]
  }
]
