[
  {
    "label": "Overview",
    "style": "default",
    "rows": [
      [
        {
          "name": "name"
        },
        {
          "name": "isActive"
        }
      ],
      [
        {
          "name": "type"
        },
        {
          "name": "inBackground"
        }
      ],
      [
        {
          "name": "usage"
        },
        {
          "name": "sourceEntity"
        }
      ],
      [
        {
          "name": "massAction"
        },
        {
          "name": "display"
        }
      ]
    ]
  },
  {
    "label": "Parameters",
    "style": "default",
    "dynamicLogicVisible": {
      "conditionGroup": [
        {
          "type": "in",
          "attribute": "type",
          "value": [
            "webhook",
            "email",
            "create",
            "update",
            "error",
            "upsert"
          ]
        }
      ]
    },
    "rows": [
      [
        {
          "name": "webhookUrl"
        },
        false
      ]
    ]
  }
]